criteria_pattern/__init__.py
criteria_pattern/criteria.py
criteria_pattern/filter.py
criteria_pattern/filter_operator.py
criteria_pattern/order.py
criteria_pattern/order_direction.py
criteria_pattern/py.typed
criteria_pattern/converter/__init__.py
criteria_pattern/converter/sql_converter.py
criteria_pattern/exceptions/__init__.py
criteria_pattern/exceptions/invalid_column_error.py
criteria_pattern/exceptions/invalid_table_error.py
criteria_pattern/exceptions/sql_converter_error.py
criteria_pattern-2024.11.5.dist-info/METADATA
criteria_pattern-2024.11.5.dist-info/WHEEL
criteria_pattern-2024.11.5.dist-info/licenses/LICENSE.md
criteria_pattern-2024.11.5.dist-info/RECORD
