Metadata-Version: 2.3
Name: criteria-pattern
Version: 2024.11.5
Summary: The "Criteria Pattern" is a Python package that simplifies and standardizes criteria based filtering, validation and selection.
Project-URL: Homepage, https://github.com/adriamontoto/criteria-pattern
Project-URL: Repository, https://github.com/adriamontoto/criteria-pattern
Project-URL: Issues, https://github.com/adriamontoto/criteria-pattern/issues
Author: Adria Montoto
License-Expression: MIT
License-File: LICENSE.md
Keywords: criteria,development,filtering,pattern,python,selection,tools,utilities,validation
Classifier: Intended Audience :: Developers
Classifier: License :: OSI Approved :: MIT License
Classifier: Operating System :: OS Independent
Classifier: Programming Language :: Python
Classifier: Programming Language :: Python :: 3
Classifier: Programming Language :: Python :: 3.11
Classifier: Programming Language :: Python :: 3.12
Classifier: Programming Language :: Python :: 3.13
Classifier: Typing :: Typed
Requires-Python: >=3.11
Provides-Extra: tests
Requires-Dist: bandit<2.0.0,>=1.0.0; extra == 'tests'
Requires-Dist: coverage[toml]<8.0.0,>=7.0.0; extra == 'tests'
Requires-Dist: faker<29.0.0,>=28.0.0; extra == 'tests'
Requires-Dist: mypy[reports]<2.0.0,>=1.0.0; extra == 'tests'
Requires-Dist: pre-commit<4.0.0,>=3.0.0; extra == 'tests'
Requires-Dist: pytest-asyncio<1.0.0,>=0.0.0; extra == 'tests'
Requires-Dist: pytest-randomly<4.0.0,>=3.0.0; extra == 'tests'
Requires-Dist: pytest<9.0.0,>=8.0.0; extra == 'tests'
Requires-Dist: ruff<1.0.0,>=0.0.0; extra == 'tests'
